kernel_openmodelica/__init__.py
kernel_openmodelica/__main__.py
kernel_openmodelica/kernel.py
kernel_openmodelica/data/dygraph-combined.js
kernel_openmodelica/data/kernel.json
kernel_openmodelica/data/logo-32x32.png
kernel_openmodelica/data/logo-64x64.png
kernel_openmodelica-0.1.1.data/data/share/jupyter/kernels/kernel_openmodelica/kernel.json
kernel_openmodelica-0.1.1.data/data/share/jupyter/kernels/kernel_openmodelica/logo-32x32.png
kernel_openmodelica-0.1.1.data/data/share/jupyter/kernels/kernel_openmodelica/logo-64x64.png
kernel_openmodelica-0.1.1.dist-info/LICENSE.txt
kernel_openmodelica-0.1.1.dist-info/METADATA
kernel_openmodelica-0.1.1.dist-info/WHEEL
kernel_openmodelica-0.1.1.dist-info/top_level.txt
kernel_openmodelica-0.1.1.dist-info/RECORD
