Metadata-Version: 2.1
Name: kernel-openmodelica
Version: 0.1.1
Summary: A Jupyter kernel for OpenModelica.
Home-page: https://github.com/WallyTutor/learning-scientific-computing/tree/main/tools/jupyter-kernel-openmodelica
Author: ArunKumar Palanisamy
Author-email: arunkumar.palanisamy@liu.se
Maintainer: "Walter Dal'Maz Silva"
Maintainer-email: walter.dalmazsilva@gmail.com
License: MIT
Download-URL: https://github.com/WallyTutor/learning-scientific-computing/tools/jupyter-kernel-openmodelica
Project-URL: Repository, https://github.com/WallyTutor/learning-scientific-computing/tools/jupyter-kernel-openmodelica
Keywords: Scientific computing,Computing platform
Platform: Any
Classifier: Development Status :: 3 - Alpha
Classifier: Intended Audience :: Science/Research
Classifier: License :: OSI Approved :: MIT License
Classifier: Operating System :: OS Independent
Classifier: Programming Language :: Python
Classifier: Programming Language :: Python :: 3.10
Classifier: Programming Language :: Python :: 3.11
Classifier: Topic :: Scientific/Engineering
Classifier: Topic :: Software Development
Classifier: Topic :: System :: Shells
Requires: ipykernel
Requires: jupyter_client (>=4.3.0)
Requires: majordome (>=0.3.0)
Requires: matplotlib (>=3.5.2)
Requires: numpy (>=1.22.4)
Requires: OMPython
Requires-Python: >=3.10
License-File: LICENSE.txt
Requires-Dist: ipykernel
Requires-Dist: jupyter-client (>=4.3.0)
Requires-Dist: majordome (>=0.3.0)
Requires-Dist: matplotlib (>=3.5.2)
Requires-Dist: numpy (>=1.22.4)
Requires-Dist: OMPython
